cerberus/__init__.py
cerberus/config.yaml
cerberus/start_cerberus.py
cerberus/database/__init__.py
cerberus/database/client.py
cerberus/inspect/__init__.py
cerberus/inspect/inspect.py
cerberus/invoke/__init__.py
cerberus/invoke/command.py
cerberus/kubernetes/__init__.py
cerberus/kubernetes/client.py
cerberus/prometheus/__init__.py
cerberus/prometheus/client.py
cerberus/server/__init__.py
cerberus/server/server.py
cerberus/slack/__init__.py
cerberus/slack/slack_client.py
my_last_test-1.0.1.dist-info/LICENSE
my_last_test-1.0.1.dist-info/METADATA
my_last_test-1.0.1.dist-info/WHEEL
my_last_test-1.0.1.dist-info/entry_points.txt
my_last_test-1.0.1.dist-info/top_level.txt
my_last_test-1.0.1.dist-info/RECORD
