Metadata-Version: 2.1
Name: my-last-test
Version: 1.0.1
Summary: Guardian of Kubernetes and OpenShift Clusters
Home-page: UNKNOWN
Author: yashashreesuresh
Author-email: yashashreesuresh@gmail.com
License: mit
Platform: UNKNOWN
Classifier: Development Status :: 4 - Beta
Classifier: Programming Language :: Python
Requires-Dist: setuptools
Requires-Dist: PyYAML
Requires-Dist: requests
Requires-Dist: kubernetes
Requires-Dist: datetime
Requires-Dist: configparser
Requires-Dist: slackclient
Requires-Dist: pyfiglet
Requires-Dist: prometheus-api-client
